chartsh.py
chartsh-0.1.dist-info/WHEEL
chartsh-0.1.dist-info/METADATA
chartsh-0.1.dist-info/RECORD
