Metadata-Version: 2.1
Name: chartsh
Version: 0.1
Summary: Seamlessly uploading altair charts to chartsh.com
Home-page: http://chartsh.com/ingest/docs/
License: UNKNOWN
Author: Joe Mountford
Author-email: jbm112358@gmail.com
